httpquick/__init__.py
httpquick/main.py
LICENSE
README.md
httpquick-0.1.1.dist-info/entry_points.txt
httpquick-0.1.1.dist-info/LICENSE
httpquick-0.1.1.dist-info/METADATA
httpquick-0.1.1.dist-info/WHEEL
httpquick-0.1.1.dist-info/RECORD
