Metadata-Version: 2.1
Name: httpquick
Version: 0.1.1
Summary: A HttpQuick that executes on the command line to make http requests
Home-page: https://github.com/mi-ztyanya/HttpQuick/
License: MIT
Author: mi-ztyanya
Requires-Python: >=3.8,<4.0
Classifier: License :: OSI Approved :: MIT License
Classifier: Programming Language :: Python :: 3
Classifier: Programming Language :: Python :: 3.8
Classifier: Programming Language :: Python :: 3.9
Classifier: Programming Language :: Python :: 3.10
Classifier: Programming Language :: Python :: 3.11
Classifier: Programming Language :: Python :: 3.12
Requires-Dist: certifi (>=2024.6.2,<2025.0.0)
Requires-Dist: chardet (>=5.2.0,<6.0.0)
Requires-Dist: cryptography (>=42.0.8,<43.0.0)
Requires-Dist: idna (>=3.7,<4.0)
Requires-Dist: logging (>=0.4.9.6,<0.5.0.0)
Requires-Dist: pyreadline3 (>=3.4.1,<4.0.0)
Requires-Dist: requests (>=2.32.3,<3.0.0)
Requires-Dist: urllib3 (>=2.2.2,<3.0.0)
